gpsdaemon/__init__.py
gpsdaemon/__main__.py
gpsdaemon/client.py
gpsdaemon/daemon.py
gpsdaemon/keys.py
carpi_gpsdaemon-0.2.3.dist-info/LICENSE
carpi_gpsdaemon-0.2.3.dist-info/METADATA
carpi_gpsdaemon-0.2.3.dist-info/WHEEL
carpi_gpsdaemon-0.2.3.dist-info/top_level.txt
carpi_gpsdaemon-0.2.3.dist-info/RECORD
