Metadata-Version: 2.1
Name: carpi-gpsdaemon
Version: 0.2.3
Summary: GPS daemon written in Python transmitting from GPSD to a Redis Data Bus
Home-page: https://github.com/rGunti/CarPi-GPSDaemon
Author: Raphael "rGunti" Guntersweiler
Author-email: raphael@rgunti.ch
License: MIT
Keywords: carpi gps daemon
Platform: UNKNOWN
Classifier: Development Status :: 3 - Alpha
Classifier: License :: OSI Approved :: MIT License
Classifier: Programming Language :: Python :: 3.6
Requires-Dist: wheel
Requires-Dist: carpi-redisdatabus
Requires-Dist: carpi-daemoncommons
